<api>
<package name="com.usebutton.sdk"
>
<class name="Button"
 extends="ButtonPrivate"
 abstract="false"
 static="false"
 final="false"
 deprecated="not deprecated"
 visibility="public"
>
<method name="getButton"
 return="com.usebutton.sdk.Button"
 abstract="false"
 native="false"
 synchronized="true"
 static="true"
 final="false"
 deprecated="not deprecated"
 visibility="public"
>
<parameter name="context" type="android.content.Context">
</parameter>
</method>
<method name="getButtonContext"
 return="android.content.Context"
 abstract="false"
 native="false"
 synchronized="false"
 static="true"
 final="false"
 deprecated="not deprecated"
 visibility="public"
>
</method>
<method name="isStarted"
 return="boolean"
 abstract="false"
 native="false"
 synchronized="false"
 static="true"
 final="false"
 deprecated="not deprecated"
 visibility="public"
>
</method>
<method name="logout"
 return="void"
 abstract="false"
 native="false"
 synchronized="false"
 static="false"
 final="false"
 deprecated="not deprecated"
 visibility="public"
>
</method>
<method name="start"
 return="void"
 abstract="false"
 native="false"
 synchronized="false"
 static="false"
 final="false"
 deprecated="not deprecated"
 visibility="public"
>
</method>
<method name="stop"
 return="void"
 abstract="false"
 native="false"
 synchronized="false"
 static="false"
 final="false"
 deprecated="not deprecated"
 visibility="public"
>
</method>
<method name="willDisplayPromotion"
 return="void"
 abstract="false"
 native="false"
 synchronized="false"
 static="false"
 final="false"
 deprecated="not deprecated"
 visibility="public"
>
<parameter name="placementId" type="java.lang.String">
</parameter>
<parameter name="context" type="com.usebutton.sdk.PlacementContext">
</parameter>
<parameter name="listener" type="com.usebutton.sdk.ButtonDropin.Listener">
</parameter>
</method>
</class>
<class name="ButtonDropin"
 extends="android.widget.FrameLayout"
 abstract="false"
 static="false"
 final="false"
 deprecated="not deprecated"
 visibility="public"
>
<constructor name="ButtonDropin"
 type="com.usebutton.sdk.ButtonDropin"
 static="false"
 final="false"
 deprecated="not deprecated"
 visibility="public"
>
<parameter name="context" type="android.content.Context">
</parameter>
</constructor>
<constructor name="ButtonDropin"
 type="com.usebutton.sdk.ButtonDropin"
 static="false"
 final="false"
 deprecated="not deprecated"
 visibility="public"
>
<parameter name="context" type="android.content.Context">
</parameter>
<parameter name="attrs" type="android.util.AttributeSet">
</parameter>
</constructor>
<constructor name="ButtonDropin"
 type="com.usebutton.sdk.ButtonDropin"
 static="false"
 final="false"
 deprecated="not deprecated"
 visibility="public"
>
<parameter name="context" type="android.content.Context">
</parameter>
<parameter name="attrs" type="android.util.AttributeSet">
</parameter>
<parameter name="defStyleAttr" type="int">
</parameter>
</constructor>
<constructor name="ButtonDropin"
 type="com.usebutton.sdk.ButtonDropin"
 static="false"
 final="false"
 deprecated="not deprecated"
 visibility="public"
>
<parameter name="context" type="android.content.Context">
</parameter>
<parameter name="attrs" type="android.util.AttributeSet">
</parameter>
<parameter name="defStyleAttr" type="int">
</parameter>
<parameter name="defStyleRes" type="int">
</parameter>
</constructor>
<method name="observable"
 return="&lt;any&gt;"
 abstract="false"
 native="false"
 synchronized="false"
 static="false"
 final="false"
 deprecated="not deprecated"
 visibility="public"
>
</method>
<method name="prepareForDisplayWithContext"
 return="void"
 abstract="false"
 native="false"
 synchronized="false"
 static="false"
 final="false"
 deprecated="not deprecated"
 visibility="public"
>
<parameter name="context" type="com.usebutton.sdk.PlacementContext">
</parameter>
</method>
<method name="prepareForDisplayWithContext"
 return="void"
 abstract="false"
 native="false"
 synchronized="false"
 static="false"
 final="false"
 deprecated="not deprecated"
 visibility="public"
>
<parameter name="context" type="com.usebutton.sdk.PlacementContext">
</parameter>
<parameter name="listener" type="com.usebutton.sdk.ButtonDropin.Listener">
</parameter>
</method>
<method name="refresh"
 return="void"
 abstract="false"
 native="false"
 synchronized="false"
 static="false"
 final="false"
 deprecated="not deprecated"
 visibility="public"
>
</method>
<method name="setListener"
 return="void"
 abstract="false"
 native="false"
 synchronized="false"
 static="false"
 final="false"
 deprecated="not deprecated"
 visibility="public"
>
<parameter name="listener" type="com.usebutton.sdk.ButtonDropin.Listener">
</parameter>
</method>
<method name="test_setPresenter"
 return="void"
 abstract="false"
 native="false"
 synchronized="false"
 static="false"
 final="false"
 deprecated="not deprecated"
 visibility="public"
>
<parameter name="presenter" type="DropinPresenter">
</parameter>
</method>
</class>
<interface name="ButtonDropin.Listener"
 abstract="true"
 static="true"
 final="false"
 deprecated="not deprecated"
 visibility="public"
>
<method name="onPrepared"
 return="void"
 abstract="true"
 native="false"
 synchronized="false"
 static="false"
 final="false"
 deprecated="not deprecated"
 visibility="public"
>
<parameter name="willDisplay" type="boolean">
</parameter>
</method>
</interface>
<interface name="ButtonDropin.OnDropinEvents"
 abstract="true"
 static="true"
 final="false"
 deprecated="not deprecated"
 visibility="public"
>
<method name="onAttached"
 return="void"
 abstract="true"
 native="false"
 synchronized="false"
 static="false"
 final="false"
 deprecated="not deprecated"
 visibility="public"
>
</method>
<method name="onDetached"
 return="void"
 abstract="true"
 native="false"
 synchronized="false"
 static="false"
 final="false"
 deprecated="not deprecated"
 visibility="public"
>
</method>
<method name="onDraw"
 return="void"
 abstract="true"
 native="false"
 synchronized="false"
 static="false"
 final="false"
 deprecated="not deprecated"
 visibility="public"
>
</method>
</interface>
<class name="PlacementContext"
 extends="org.json.JSONObject"
 abstract="false"
 static="false"
 final="false"
 deprecated="not deprecated"
 visibility="public"
>
<implements name="android.os.Parcelable">
</implements>
<constructor name="PlacementContext"
 type="com.usebutton.sdk.PlacementContext"
 static="false"
 final="false"
 deprecated="not deprecated"
 visibility="public"
>
<parameter name="map" type="java.util.Map&lt;java.lang.String, java.lang.String&gt;">
</parameter>
</constructor>
<constructor name="PlacementContext"
 type="com.usebutton.sdk.PlacementContext"
 static="false"
 final="false"
 deprecated="not deprecated"
 visibility="public"
>
</constructor>
<constructor name="PlacementContext"
 type="com.usebutton.sdk.PlacementContext"
 static="false"
 final="false"
 deprecated="not deprecated"
 visibility="public"
>
<parameter name="source" type="android.os.Parcel">
</parameter>
<exception name="JSONException" type="org.json.JSONException">
</exception>
</constructor>
<method name="describeContents"
 return="int"
 abstract="false"
 native="false"
 synchronized="false"
 static="false"
 final="false"
 deprecated="not deprecated"
 visibility="public"
>
</method>
<method name="forEndLocation"
 return="com.usebutton.sdk.PlacementContext"
 abstract="false"
 native="false"
 synchronized="false"
 static="true"
 final="false"
 deprecated="not deprecated"
 visibility="public"
>
<parameter name="locationName" type="java.lang.String">
</parameter>
<parameter name="location" type="android.location.Location">
</parameter>
</method>
<method name="forEndLocation"
 return="com.usebutton.sdk.PlacementContext"
 abstract="false"
 native="false"
 synchronized="false"
 static="true"
 final="false"
 deprecated="not deprecated"
 visibility="public"
>
<parameter name="locationName" type="java.lang.String">
</parameter>
<parameter name="latitude" type="double">
</parameter>
<parameter name="longitude" type="double">
</parameter>
</method>
<method name="fromMap"
 return="com.usebutton.sdk.PlacementContext"
 abstract="false"
 native="false"
 synchronized="false"
 static="true"
 final="false"
 deprecated="not deprecated"
 visibility="public"
>
<parameter name="map" type="java.util.Map&lt;java.lang.String, java.lang.String&gt;">
</parameter>
</method>
<method name="getEndLocation"
 return="com.usebutton.sdk.util.LatLngPair"
 abstract="false"
 native="false"
 synchronized="false"
 static="false"
 final="false"
 deprecated="not deprecated"
 visibility="public"
>
</method>
<method name="getEndName"
 return="java.lang.String"
 abstract="false"
 native="false"
 synchronized="false"
 static="false"
 final="false"
 deprecated="not deprecated"
 visibility="public"
>
</method>
<method name="getStartLocation"
 return="com.usebutton.sdk.util.LatLngPair"
 abstract="false"
 native="false"
 synchronized="false"
 static="false"
 final="false"
 deprecated="not deprecated"
 visibility="public"
>
</method>
<method name="getStartName"
 return="java.lang.String"
 abstract="false"
 native="false"
 synchronized="false"
 static="false"
 final="false"
 deprecated="not deprecated"
 visibility="public"
>
</method>
<method name="withEndLocation"
 return="com.usebutton.sdk.PlacementContext"
 abstract="false"
 native="false"
 synchronized="false"
 static="false"
 final="false"
 deprecated="not deprecated"
 visibility="public"
>
<parameter name="coordinate" type="com.usebutton.sdk.util.LatLngPair">
</parameter>
</method>
<method name="withEndLocation"
 return="com.usebutton.sdk.PlacementContext"
 abstract="false"
 native="false"
 synchronized="false"
 static="false"
 final="false"
 deprecated="not deprecated"
 visibility="public"
>
<parameter name="locationName" type="java.lang.String">
</parameter>
<parameter name="coordinate" type="com.usebutton.sdk.util.LatLngPair">
</parameter>
</method>
<method name="withStartLocation"
 return="com.usebutton.sdk.PlacementContext"
 abstract="false"
 native="false"
 synchronized="false"
 static="false"
 final="false"
 deprecated="not deprecated"
 visibility="public"
>
<parameter name="coordinate" type="com.usebutton.sdk.util.LatLngPair">
</parameter>
</method>
<method name="withStartLocation"
 return="com.usebutton.sdk.PlacementContext"
 abstract="false"
 native="false"
 synchronized="false"
 static="false"
 final="false"
 deprecated="not deprecated"
 visibility="public"
>
<parameter name="locationName" type="java.lang.String">
</parameter>
<parameter name="latitude" type="double">
</parameter>
<parameter name="longitude" type="double">
</parameter>
</method>
<method name="withStartLocation"
 return="com.usebutton.sdk.PlacementContext"
 abstract="false"
 native="false"
 synchronized="false"
 static="false"
 final="false"
 deprecated="not deprecated"
 visibility="public"
>
<parameter name="locationName" type="java.lang.String">
</parameter>
<parameter name="coordinate" type="com.usebutton.sdk.util.LatLngPair">
</parameter>
</method>
<method name="writeToParcel"
 return="void"
 abstract="false"
 native="false"
 synchronized="false"
 static="false"
 final="false"
 deprecated="not deprecated"
 visibility="public"
>
<parameter name="dest" type="android.os.Parcel">
</parameter>
<parameter name="flags" type="int">
</parameter>
</method>
<field name="CREATOR"
 type="android.os.Parcelable.Creator"
 transient="false"
 volatile="false"
 static="true"
 final="false"
 deprecated="not deprecated"
 visibility="public"
>
</field>
<field name="END_LOCATION"
 type="java.lang.String"
 transient="false"
 volatile="false"
 value="&quot;end_location&quot;"
 static="true"
 final="true"
 deprecated="not deprecated"
 visibility="public"
>
</field>
<field name="KEY_DISPLAY_NAME"
 type="java.lang.String"
 transient="false"
 volatile="false"
 value="&quot;display_name&quot;"
 static="true"
 final="true"
 deprecated="not deprecated"
 visibility="public"
>
</field>
<field name="KEY_LATITUDE"
 type="java.lang.String"
 transient="false"
 volatile="false"
 value="&quot;latitude&quot;"
 static="true"
 final="true"
 deprecated="not deprecated"
 visibility="public"
>
</field>
<field name="KEY_LONGITUDE"
 type="java.lang.String"
 transient="false"
 volatile="false"
 value="&quot;longitude&quot;"
 static="true"
 final="true"
 deprecated="not deprecated"
 visibility="public"
>
</field>
<field name="START_LOCATION"
 type="java.lang.String"
 transient="false"
 volatile="false"
 value="&quot;start_location&quot;"
 static="true"
 final="true"
 deprecated="not deprecated"
 visibility="public"
>
</field>
</class>
<class name="PlacementContext.Location"
 extends="java.lang.Object"
 abstract="false"
 static="true"
 final="false"
 deprecated="not deprecated"
 visibility="public"
>
<constructor name="PlacementContext.Location"
 type="com.usebutton.sdk.PlacementContext.Location"
 static="false"
 final="false"
 deprecated="not deprecated"
 visibility="public"
>
</constructor>
</class>
</package>
<package name="com.usebutton.sdk.activity"
>
<class name="PromotionTestActivity"
 extends="android.app.Activity"
 abstract="false"
 static="false"
 final="false"
 deprecated="not deprecated"
 visibility="public"
>
<constructor name="PromotionTestActivity"
 type="com.usebutton.sdk.activity.PromotionTestActivity"
 static="false"
 final="false"
 deprecated="not deprecated"
 visibility="public"
>
</constructor>
</class>
</package>
<package name="com.usebutton.sdk.util"
>
<class name="Arrays"
 extends="java.lang.Object"
 abstract="false"
 static="false"
 final="false"
 deprecated="not deprecated"
 visibility="public"
>
<constructor name="Arrays"
 type="com.usebutton.sdk.util.Arrays"
 static="false"
 final="false"
 deprecated="not deprecated"
 visibility="public"
>
</constructor>
<method name="isEmpty"
 return="boolean"
 abstract="false"
 native="false"
 synchronized="false"
 static="true"
 final="false"
 deprecated="not deprecated"
 visibility="public"
>
<parameter name="objects" type="java.lang.Object[]">
</parameter>
</method>
<method name="isNotEmpty"
 return="boolean"
 abstract="false"
 native="false"
 synchronized="false"
 static="true"
 final="false"
 deprecated="not deprecated"
 visibility="public"
>
<parameter name="objects" type="java.lang.Object[]">
</parameter>
</method>
<method name="toString"
 return="java.lang.String"
 abstract="false"
 native="false"
 synchronized="false"
 static="true"
 final="false"
 deprecated="not deprecated"
 visibility="public"
>
<parameter name="objects" type="java.lang.Object[]">
</parameter>
</method>
</class>
<class name="IdentifierForAdvertiserProvider"
 extends="java.lang.Object"
 abstract="false"
 static="false"
 final="false"
 deprecated="not deprecated"
 visibility="public"
>
<constructor name="IdentifierForAdvertiserProvider"
 type="com.usebutton.sdk.util.IdentifierForAdvertiserProvider"
 static="false"
 final="false"
 deprecated="not deprecated"
 visibility="public"
>
<parameter name="context" type="android.content.Context">
</parameter>
</constructor>
<method name="getIdentifier"
 return="java.lang.String"
 abstract="false"
 native="false"
 synchronized="false"
 static="false"
 final="false"
 deprecated="not deprecated"
 visibility="public"
>
</method>
</class>
<class name="LatLngPair"
 extends="<any>"
 abstract="false"
 static="false"
 final="false"
 deprecated="not deprecated"
 visibility="public"
>
<constructor name="LatLngPair"
 type="com.usebutton.sdk.util.LatLngPair"
 static="false"
 final="false"
 deprecated="not deprecated"
 visibility="public"
>
<parameter name="latitude" type="java.lang.Double">
</parameter>
<parameter name="longitude" type="java.lang.Double">
</parameter>
</constructor>
<constructor name="LatLngPair"
 type="com.usebutton.sdk.util.LatLngPair"
 static="false"
 final="false"
 deprecated="not deprecated"
 visibility="public"
>
<parameter name="location" type="android.location.Location">
</parameter>
</constructor>
<method name="getLatitude"
 return="double"
 abstract="false"
 native="false"
 synchronized="false"
 static="false"
 final="false"
 deprecated="not deprecated"
 visibility="public"
>
</method>
<method name="getLongitude"
 return="double"
 abstract="false"
 native="false"
 synchronized="false"
 static="false"
 final="false"
 deprecated="not deprecated"
 visibility="public"
>
</method>
</class>
<class name="LocationProvider"
 extends="java.lang.Object"
 abstract="false"
 static="false"
 final="false"
 deprecated="not deprecated"
 visibility="public"
>
<constructor name="LocationProvider"
 type="com.usebutton.sdk.util.LocationProvider"
 static="false"
 final="false"
 deprecated="not deprecated"
 visibility="public"
>
<parameter name="context" type="android.content.Context">
</parameter>
</constructor>
<method name="getBestLocation"
 return="android.location.Location"
 abstract="false"
 native="false"
 synchronized="false"
 static="false"
 final="false"
 deprecated="not deprecated"
 visibility="public"
>
</method>
</class>
<class name="PackageObserver"
 extends="android.content.BroadcastReceiver"
 abstract="false"
 static="false"
 final="false"
 deprecated="not deprecated"
 visibility="public"
>
<constructor name="PackageObserver"
 type="com.usebutton.sdk.util.PackageObserver"
 static="false"
 final="false"
 deprecated="not deprecated"
 visibility="public"
>
<parameter name="context" type="android.content.Context">
</parameter>
</constructor>
<method name="getPackageManager"
 return="android.content.pm.PackageManager"
 abstract="false"
 native="false"
 synchronized="false"
 static="false"
 final="false"
 deprecated="not deprecated"
 visibility="public"
>
</method>
<method name="isInstalled"
 return="boolean"
 abstract="false"
 native="false"
 synchronized="false"
 static="false"
 final="false"
 deprecated="not deprecated"
 visibility="public"
>
<parameter name="packageName" type="java.lang.String">
</parameter>
</method>
<method name="observePackage"
 return="void"
 abstract="false"
 native="false"
 synchronized="false"
 static="false"
 final="false"
 deprecated="not deprecated"
 visibility="public"
>
<parameter name="packageName" type="java.lang.String">
</parameter>
<parameter name="changeObserver" type="com.usebutton.sdk.util.Receiver&lt;android.content.pm.PackageInfo&gt;">
</parameter>
</method>
<method name="onReceive"
 return="void"
 abstract="false"
 native="false"
 synchronized="false"
 static="false"
 final="false"
 deprecated="not deprecated"
 visibility="public"
>
<parameter name="context" type="android.content.Context">
</parameter>
<parameter name="intent" type="android.content.Intent">
</parameter>
</method>
<method name="removeObserver"
 return="void"
 abstract="false"
 native="false"
 synchronized="false"
 static="false"
 final="false"
 deprecated="not deprecated"
 visibility="public"
>
<parameter name="observer" type="com.usebutton.sdk.util.Receiver&lt;android.content.pm.PackageInfo&gt;">
</parameter>
</method>
<method name="stop"
 return="void"
 abstract="false"
 native="false"
 synchronized="false"
 static="false"
 final="false"
 deprecated="not deprecated"
 visibility="public"
>
</method>
</class>
<interface name="Receiver"
 abstract="true"
 static="false"
 final="false"
 deprecated="not deprecated"
 visibility="public"
>
<method name="receive"
 return="void"
 abstract="true"
 native="false"
 synchronized="false"
 static="false"
 final="false"
 deprecated="not deprecated"
 visibility="public"
>
<parameter name="object" type="T">
</parameter>
</method>
</interface>
</package>
</api>
